SignerPy/ByteBuf.py
SignerPy/Simon.py
SignerPy/Sm3.py
SignerPy/__init__.py
SignerPy/argus.py
SignerPy/gorgon.py
SignerPy/ladon.py
SignerPy/pkcs7_padding.py
SignerPy/protobuf.py
signerpy-0.6.dist-info/licenses/LICENSE.txt
signerpy-0.6.dist-info/METADATA
signerpy-0.6.dist-info/WHEEL
signerpy-0.6.dist-info/top_level.txt
signerpy-0.6.dist-info/RECORD
