Metadata-Version: 2.4
Name: SignerPy
Version: 0.6
Summary: Signture TikTok Headers and More
Author: L7N
Author-email: l7ng4q@gmail.com
Classifier: Programming Language :: Python :: 3
Classifier: License :: OSI Approved :: MIT License
Classifier: Operating System :: OS Independent
Requires-Python: >=3.6
License-File: LICENSE.txt
Requires-Dist: user_agent
Requires-Dist: requests
Requires-Dist: pycryptodome
Dynamic: author
Dynamic: author-email
Dynamic: classifier
Dynamic: license-file
Dynamic: requires-dist
Dynamic: requires-python
Dynamic: summary
